{
  "data": [
    {
      "value": "ENERO",
      "selected": true,
      "name": "ENERO"
    },
    {
      "value": "FEBRERO",
      "selected": false,
      "name": "FEBRERO"
    },
    {
      "value": "MARZO",
      "selected": false,
      "name": "MARZO"
    },
    {
      "value": "ABRIL",
      "selected": false,
      "name": "ABRIL"
    },
    {
      "value": "MAYO",
      "selected": false,
      "name": "MAYO"
    },
    {
      "value": "JUNIO",
      "selected": false,
      "name": "JUNIO"
    },
    {
      "value": "JULIO",
      "selected": false,
      "name": "JULIO"
    },
    {
      "value": "AGOSTO",
      "selected": false,
      "name": "AGOSTO"
    },
    {
      "value": "SEPTIEMBRE",
      "selected": false,
      "name": "SEPTIEMBRE"
    },
    {
      "value": "OCTUBRE",
      "selected": false,
      "name": "OCTUBRE"
    },
    {
      "value": "NOVIEMBRE",
      "selected": false,
      "name": "NOVIEMBRE"
    },
    {
      "value": "DICIEMBRE",
      "selected": false,
      "name": "DICIEMBRE"
    }
  ]
}
